pyrlu-0.2.1.dist-info/METADATA
pyrlu-0.2.1.dist-info/WHEEL
pyrlu-0.2.1.dist-info/license_files/LICENSE
pyrlu/__init__.py
pyrlu/__init__.pyi
pyrlu/py.typed
pyrlu/pyrlu.cpython-39-aarch64-linux-gnu.so
pyrlu-0.2.1.dist-info/RECORD
